xmov_oss/__init__.py
xmov_oss/__main__.py
xmov_oss/args.py
xmov_oss/core.py
xmov_oss/rich_console.py
xmov_oss/schema.py
xmov_oss/utils.py
xmov_oss-1.0.8.dist-info/METADATA
xmov_oss-1.0.8.dist-info/WHEEL
xmov_oss-1.0.8.dist-info/entry_points.txt
xmov_oss-1.0.8.dist-info/top_level.txt
xmov_oss-1.0.8.dist-info/RECORD
