Metadata-Version: 2.1
Name: xmov_oss
Version: 1.0.8
Summary: A Python library for xmov_oss
Author: xmov_oss
License: MIT
Project-URL: Homepage, https://pypi.org/project/xmov_oss/
Project-URL: Repository, https://github.com/xmov/xmov_oss
Keywords: python,xmov_oss
Classifier: Development Status :: 3 - Alpha
Classifier: Intended Audience :: Developers
Classifier: License :: OSI Approved :: MIT License
Classifier: Operating System :: OS Independent
Classifier: Programming Language :: Python :: 3
Classifier: Programming Language :: Python :: 3.6
Classifier: Programming Language :: Python :: 3.7
Classifier: Programming Language :: Python :: 3.8
Classifier: Programming Language :: Python :: 3.9
Classifier: Programming Language :: Python :: 3.10
Classifier: Programming Language :: Python :: 3.11
Classifier: Programming Language :: Python :: 3.12
Classifier: Topic :: Software Development :: Libraries :: Python Modules
Requires-Python: >=3.6
Requires-Dist: oss2>=2.0.0
Requires-Dist: PyJWT>=2.0.0
Provides-Extra: dev
Requires-Dist: twine; extra == "dev"
Requires-Dist: pip-tools; extra == "dev"
Requires-Dist: build; extra == "dev"
Requires-Dist: pytest>=6.0; extra == "dev"
Requires-Dist: pytest-cov>=2.0; extra == "dev"
Requires-Dist: black>=22.0; extra == "dev"
Requires-Dist: flake8>=4.0; extra == "dev"
Requires-Dist: mypy>=0.900; extra == "dev"
